preview_generator/__init__.py
preview_generator/__main__.py
preview_generator/exception.py
preview_generator/file_converter.py
preview_generator/infos.py
preview_generator/manager.py
preview_generator/utils.py
preview_generator/preview/__init__.py
preview_generator/preview/builder_factory.py
preview_generator/preview/generic_preview.py
preview_generator/preview/mime.py
preview_generator/preview/builder/__init__.py
preview_generator/preview/builder/archive__zip.py
preview_generator/preview/builder/document__scribus.py
preview_generator/preview/builder/document_generic.py
preview_generator/preview/builder/fcntl_ivc.py
preview_generator/preview/builder/image__imconvert.py
preview_generator/preview/builder/image__inkscape.py
preview_generator/preview/builder/image__pillow.py
preview_generator/preview/builder/image__wand.py
preview_generator/preview/builder/office__libreoffice.py
preview_generator/preview/builder/pdf__pypdf2.py
preview_generator/preview/builder/plain_text.py
preview_generator/preview/builder/xvfbwrapper.py
preview_generator/preview/scripts/__init__.py
preview_generator/preview/scripts/scribus_sla_to_pdf.py
tests/__init__.py
tests/deprecatedtest_eps_input.py
tests/test_builder_factory.py
tests/test_manager.py
tests/test_utils.py
tests/input/__init__.py
tests/input/image.py
tests/input/bmp/__init__.py
tests/input/bmp/test_bmp.py
tests/input/eps/__init__.py
tests/input/eps/test_eps.py
tests/input/gif/__init__.py
tests/input/gif/test_gif.py
tests/input/jpeg/__init__.py
tests/input/jpeg/test_jpeg.py
tests/input/odt/__init__.py
tests/input/odt/test_odt.py
tests/input/pdf/__init__.py
tests/input/pdf/test_pdf.py
tests/input/png/__init__.py
tests/input/png/test_png.py
tests/input/sla/__init__.py
tests/input/sla/test_sla.py
tests/input/svg/__init__.py
tests/input/svg/test_svg.py
tests/input/txt/__init__.py
tests/input/txt/test_txt.py
tests/input/xcf/__init__.py
tests/input/xcf/test_xcf.py
tests/input/xlsx/__init__.py
tests/input/xlsx/test_xlsx.py
preview_generator_ivc-0.11.11.dist-info/METADATA
preview_generator_ivc-0.11.11.dist-info/WHEEL
preview_generator_ivc-0.11.11.dist-info/entry_points.txt
preview_generator_ivc-0.11.11.dist-info/top_level.txt
preview_generator_ivc-0.11.11.dist-info/RECORD
