Metadata-Version: 2.1
Name: preview-generator-ivc
Version: 0.11.11
Summary: A library for generating preview (thumbnails, text or json overview) for file-based content
Home-page: https://github.com/ivc-inform/preview-generator.git
Author: Algoo
Author-email: contact@algoo.fr
License: UNKNOWN
Download-URL: https://github.com/algoo/preview-generator/archive/release_0.11.11.tar.gz
Keywords: preview,preview_generator,thumbnail,cache
Platform: UNKNOWN
Classifier: Programming Language :: Python :: 3.5
Classifier: Programming Language :: Python :: 3.6
Classifier: Programming Language :: Python :: 3.7
Requires-Python: >= 3.6
Provides-Extra: dev
Requires-Dist: pytest ; extra == 'dev'
Requires-Dist: flake8 ; extra == 'dev'
Requires-Dist: isort ; extra == 'dev'
Requires-Dist: mypy ; extra == 'dev'
Requires-Dist: pre-commit ; extra == 'dev'
Requires-Dist: black ; extra == 'dev'
Provides-Extra: testing
Requires-Dist: pytest ; extra == 'testing'
